setup.py
pysns/__init__.py
pysns.egg-info/PKG-INFO
pysns.egg-info/SOURCES.txt
pysns.egg-info/dependency_links.txt
pysns.egg-info/requires.txt
pysns.egg-info/top_level.txt
pysns/adapter/__init__.py
pysns/adapter/base.py
pysns/adapter/exception.py
pysns/adapter/weibo.py
pysns/adapter/weixin.py