Metadata-Version: 1.1
Name: pysns
Version: 0.0.5
Summary: Third-party login
Home-page: http://github.com/zakzou/pysns
Author: zakzou
Author-email: zakzou@live.com
License: MIT
Keywords: OAuth2 Client,OAuth2,Login
Platform: any
Classifier: Environment :: Web Environment
Classifier: Intended Audience :: Developers
Classifier: License :: OSI Approved :: MIT License
Classifier: Operating System :: OS Independent
Classifier: Programming Language :: Python
